AI/BASE.py
AI/__init__.py
AI/prompts.py
gemini_interpreter-0.1.5.dist-info/METADATA
gemini_interpreter-0.1.5.dist-info/WHEEL
gemini_interpreter-0.1.5.dist-info/entry_points.txt
gemini_interpreter-0.1.5.dist-info/top_level.txt
gemini_interpreter-0.1.5.dist-info/RECORD
