Metadata-Version: 2.1
Name: gemini-interpreter
Version: 0.1.5
Summary: AI interpreter project
Home-page: https://github.com/Python-shik/gemini-interpreter
Author: Illya Lazarev
Author-email: sbdt.israel@gmail.com
Classifier: Programming Language :: Python :: 3
Classifier: License :: OSI Approved :: MIT License
Classifier: Operating System :: OS Independent
Requires-Python: >=3.7
Requires-Dist: requests
Requires-Dist: psutil
